magneticow/__init__.py
magneticow/__main__.py
magneticow/magneticow.py
magneticow/utils.py
magneticow/static/assets/magnet.gif
magneticow/static/fonts/NotoMono/LICENSE_OFL.txt
magneticow/static/fonts/NotoMono/Regular.ttf
magneticow/static/fonts/NotoSansUI/Bold.ttf
magneticow/static/fonts/NotoSansUI/BoldItalic.ttf
magneticow/static/fonts/NotoSansUI/Italic.ttf
magneticow/static/fonts/NotoSansUI/LICENSE_OFL.txt
magneticow/static/fonts/NotoSansUI/Regular.ttf
magneticow/static/scripts/plotly-v1.26.1.min.js
magneticow/static/scripts/statistics.js
magneticow/static/scripts/torrent.js
magneticow/static/styles/essential.css
magneticow/static/styles/homepage.css
magneticow/static/styles/reset.css
magneticow/static/styles/statistics.css
magneticow/static/styles/torrent.css
magneticow/static/styles/torrents.css
magneticow/templates/homepage.html
magneticow/templates/statistics.html
magneticow/templates/torrent.html
magneticow/templates/torrents.html
magneticow-0.6.0.dist-info/DESCRIPTION.rst
magneticow-0.6.0.dist-info/METADATA
magneticow-0.6.0.dist-info/RECORD
magneticow-0.6.0.dist-info/WHEEL
magneticow-0.6.0.dist-info/entry_points.txt
magneticow-0.6.0.dist-info/metadata.json
magneticow-0.6.0.dist-info/top_level.txt
