Metadata-Version: 2.0
Name: magneticow
Version: 0.6.0
Summary: Lightweight web interface for magnetico.
Home-page: http://magnetico.org
Author: Mert Bora ALPER
Author-email: bora@boramalper.org
License: GNU Affero General Public License v3 or later (AGPLv3+)
Platform: UNKNOWN
Classifier: Development Status :: 2 - Pre-Alpha
Classifier: Environment :: Web Environment
Classifier: Intended Audience :: End Users/Desktop
Classifier: License :: OSI Approved :: GNU Affero General Public License v3 or later (AGPLv3+)
Classifier: Natural Language :: English
Classifier: Operating System :: POSIX :: Linux
Classifier: Programming Language :: Python :: 3 :: Only
Classifier: Programming Language :: Python :: Implementation :: CPython
Requires-Dist: appdirs (>=1.4.3)
Requires-Dist: flask (>=0.12.1)
Requires-Dist: gevent (>=1.2.1)
